{
  "id": "hvdv-ngn-ao-033_ver_03",
  "name": "Hoa dây và trái bầu - HVĐV---NGN---AO---033_ver_03",
  "source_url": "https://hoavandaiviet.vn/product/hvdv-ngn-ao-033_ver_03/",
  "image_url": "https://hoavandaiviet.vn/wp-content/uploads/2020/03/HVDV-NGN-AO-033_ver_03.jpg",
  "period": "Nguyen",
  "source_site": "hoavandaiviet.vn",
  "license_note": "Free image - vector file sold separately",
  "downloaded_at": "2026-03-29T08:35:16.000903+00:00",
  "style": "colored",
  "multi_motif": false,
  "motif_subject": "Hoa dây và trái bầu, dệt trên đoạn",
  "artifact_source": "Hoa văn trên áo dài bát bửu, bảo tàng văn hóa Huế"
}