{
  "id": "vlhd-ds-lv-024",
  "name": "VLHD-DS-LV-024",
  "source_url": "https://hoavandaiviet.vn/product/vlhd-ds-lv-024/",
  "image_url": "https://hoavandaiviet.vn/wp-content/uploads/2024/01/VLHD-DS-LV-023.jpg",
  "period": "Co-Dai",
  "source_site": "hoavandaiviet.vn",
  "license_note": "Free image - vector file sold separately",
  "downloaded_at": "2026-03-29T08:51:22.907941+00:00",
  "style": "line_art",
  "multi_motif": false,
  "motif_subject": "Hoa văn các loài vật trên trống đồng.",
  "artifact_source": "Tạp chí Khảo cổ học số 14: Chuyên Đề – Trống Đồng. 1974."
}